rao_algorithms/__init__.py
rao_algorithms/algorithms.py
rao_algorithms/objective_functions.py
rao_algorithms/optimization.py
rao_algorithms/penalty.py
rao_algorithms/samyama_optimization.cpython-38-x86_64-linux-gnu.so
rao_algorithms-0.9.3.dist-info/METADATA
rao_algorithms-0.9.3.dist-info/WHEEL
rao_algorithms-0.9.3.dist-info/licenses/LICENSE
rao_algorithms-0.9.3.dist-info/RECORD
