Metadata-Version: 2.4
Name: rao-algorithms
Version: 0.9.3
Classifier: Programming Language :: Python :: 3
Classifier: Programming Language :: Rust
Classifier: License :: OSI Approved :: MIT License
Classifier: Operating System :: OS Independent
Classifier: Topic :: Scientific/Engineering :: Mathematics
Requires-Dist: numpy>=1.20
License-File: LICENSE
Summary: High-performance optimization algorithms by Prof. R.V. Rao (Jaya, Rao, TLBO) backed by Rust
Author-email: Sandeep Kunkunuru <sandeep.kunkunuru@gmail.com>
License: MIT
Requires-Python: >=3.8
